opensemantic/characteristics/quantitative/__init__.py
opensemantic/characteristics/quantitative/_model.py
opensemantic/characteristics/quantitative/_static.py
opensemantic_characteristics_quantitative-0.2.4.dev0.dist-info/licenses/LICENSE.txt
opensemantic_characteristics_quantitative-0.2.4.dev0.dist-info/METADATA
opensemantic_characteristics_quantitative-0.2.4.dev0.dist-info/WHEEL
opensemantic_characteristics_quantitative-0.2.4.dev0.dist-info/top_level.txt
opensemantic_characteristics_quantitative-0.2.4.dev0.dist-info/RECORD
