Metadata-Version: 2.4
Name: opensemantic.characteristics.quantitative
Version: 0.2.4.dev0
Summary: Library with Python models derived from the page package world.opensemantic.characteristics.quantitative
Home-page: https://github.com/OpenSemanticWorld-Packages/opensemantic.characteristics.quantitative-python
Author: OpenSemanticWorld
Author-email: team@opensemantic.world
License: Apache 2.0
Project-URL: Documentation, https://github.com/OpenSemanticWorld-Packages/opensemantic.characteristics.quantitative-python
Project-URL: Source, https://github.com/pyscaffold/pyscaffold/
Project-URL: Tracker, https://github.com/pyscaffold/pyscaffold/issues
Platform: any
Classifier: Development Status :: 4 - Beta
Classifier: Programming Language :: Python
Requires-Python: >=3.11
License-File: LICENSE.txt
Requires-Dist: pydantic
Requires-Dist: pint
Requires-Dist: pint-pandas
Requires-Dist: oold
Requires-Dist: opensemantic.characteristics
Provides-Extra: testing
Requires-Dist: setuptools; extra == "testing"
Requires-Dist: pytest; extra == "testing"
Requires-Dist: pytest-cov; extra == "testing"
Requires-Dist: scipy; extra == "testing"
Dynamic: license-file
